Workbook

Sheet Custo por Peca
A1: Leilão de Bonecos 3D — Custo e Lance Mínimo
A2: Bambu Lab A1 · TikTok Shop. Preencha apenas as células AMARELAS (texto azul).
A4: PREMISSAS
A5: Preço do filamento (R$/kg) | B5: 110
A6: Tarifa de energia (R$/kWh) | B6: 0.95
A7: Potência média da A1 (W) | B7: 100
A8: Embalagem + etiqueta (R$/peça) | B8: 4
A9: Taxa de falha / refugo (%) | B9: 0.1
A10: Desgaste e manutenção (R$/hora) | B10: 0.5
A11: Comissão do marketplace (%) | B11: 0.08
A12: Seu custo por hora (R$) | B12: 25
A13: Multiplicador de preço-alvo (x) | B13: 3
A15: PEÇAS | D15: Preencha as 4 primeiras colunas. O resto é calculado.
A16: Peça | B16: Peso (g) | C16: Impressão (h) | D16: Manuseio (min) | E16: Filamento | F16: Energia | G16: Embalagem | H16: Desgaste | I16: Seu tempo | J16: Subtotal | K16: Refugo | L16: CUSTO TOTAL | M16: LANCE MÍNIMO | N16: Preço-alvo | O16: Lucro no alvo | P16: Margem
A17: Dragão articulado M (exemplo) | B17: 95 | C17: 5.5 | D17: 8 | E17: =IF($B17="","",$B17*$B$5/1000) | F17: =IF($B17="","",$C17*$B$7/1000*$B$6) | G17: =IF($B17="","",$B$8) | H17: =IF($B17="","",$C17*$B$10) | I17: =IF($B17="","",$D17/60*$B$12) | J17: =IF($B17="","",SUM($E17:$I17)) | K17: =IF($B17="","",$J17*$B$9) | L17: =IF($B17="","",$J17+$K17) | M17: =IFERROR(CEILING($L17/(1-$B$11),1),"") | N17: =IFERROR(CEILING($L17*$B$13/(1-$B$11),1),"") | O17: =IFERROR($N17*(1-$B$11)-$L17,"") | P17: =IFERROR($O17/$N17,"")
E18: =IF($B18="","",$B18*$B$5/1000) | F18: =IF($B18="","",$C18*$B$7/1000*$B$6) | G18: =IF($B18="","",$B$8) | H18: =IF($B18="","",$C18*$B$10) | I18: =IF($B18="","",$D18/60*$B$12) | J18: =IF($B18="","",SUM($E18:$I18)) | K18: =IF($B18="","",$J18*$B$9) | L18: =IF($B18="","",$J18+$K18) | M18: =IFERROR(CEILING($L18/(1-$B$11),1),"") | N18: =IFERROR(CEILING($L18*$B$13/(1-$B$11),1),"") | O18: =IFERROR($N18*(1-$B$11)-$L18,"") | P18: =IFERROR($O18/$N18,"")
E19: =IF($B19="","",$B19*$B$5/1000) | F19: =IF($B19="","",$C19*$B$7/1000*$B$6) | G19: =IF($B19="","",$B$8) | H19: =IF($B19="","",$C19*$B$10) | I19: =IF($B19="","",$D19/60*$B$12) | J19: =IF($B19="","",SUM($E19:$I19)) | K19: =IF($B19="","",$J19*$B$9) | L19: =IF($B19="","",$J19+$K19) | M19: =IFERROR(CEILING($L19/(1-$B$11),1),"") | N19: =IFERROR(CEILING($L19*$B$13/(1-$B$11),1),"") | O19: =IFERROR($N19*(1-$B$11)-$L19,"") | P19: =IFERROR($O19/$N19,"")
E20: =IF($B20="","",$B20*$B$5/1000) | F20: =IF($B20="","",$C20*$B$7/1000*$B$6) | G20: =IF($B20="","",$B$8) | H20: =IF($B20="","",$C20*$B$10) | I20: =IF($B20="","",$D20/60*$B$12) | J20: =IF($B20="","",SUM($E20:$I20)) | K20: =IF($B20="","",$J20*$B$9) | L20: =IF($B20="","",$J20+$K20) | M20: =IFERROR(CEILING($L20/(1-$B$11),1),"") | N20: =IFERROR(CEILING($L20*$B$13/(1-$B$11),1),"") | O20: =IFERROR($N20*(1-$B$11)-$L20,"") | P20: =IFERROR($O20/$N20,"")
E21: =IF($B21="","",$B21*$B$5/1000) | F21: =IF($B21="","",$C21*$B$7/1000*$B$6) | G21: =IF($B21="","",$B$8) | H21: =IF($B21="","",$C21*$B$10) | I21: =IF($B21="","",$D21/60*$B$12) | J21: =IF($B21="","",SUM($E21:$I21)) | K21: =IF($B21="","",$J21*$B$9) | L21: =IF($B21="","",$J21+$K21) | M21: =IFERROR(CEILING($L21/(1-$B$11),1),"") | N21: =IFERROR(CEILING($L21*$B$13/(1-$B$11),1),"") | O21: =IFERROR($N21*(1-$B$11)-$L21,"") | P21: =IFERROR($O21/$N21,"")
E22: =IF($B22="","",$B22*$B$5/1000) | F22: =IF($B22="","",$C22*$B$7/1000*$B$6) | G22: =IF($B22="","",$B$8) | H22: =IF($B22="","",$C22*$B$10) | I22: =IF($B22="","",$D22/60*$B$12) | J22: =IF($B22="","",SUM($E22:$I22)) | K22: =IF($B22="","",$J22*$B$9) | L22: =IF($B22="","",$J22+$K22) | M22: =IFERROR(CEILING($L22/(1-$B$11),1),"") | N22: =IFERROR(CEILING($L22*$B$13/(1-$B$11),1),"") | O22: =IFERROR($N22*(1-$B$11)-$L22,"") | P22: =IFERROR($O22/$N22,"")
E23: =IF($B23="","",$B23*$B$5/1000) | F23: =IF($B23="","",$C23*$B$7/1000*$B$6) | G23: =IF($B23="","",$B$8) | H23: =IF($B23="","",$C23*$B$10) | I23: =IF($B23="","",$D23/60*$B$12) | J23: =IF($B23="","",SUM($E23:$I23)) | K23: =IF($B23="","",$J23*$B$9) | L23: =IF($B23="","",$J23+$K23) | M23: =IFERROR(CEILING($L23/(1-$B$11),1),"") | N23: =IFERROR(CEILING($L23*$B$13/(1-$B$11),1),"") | O23: =IFERROR($N23*(1-$B$11)-$L23,"") | P23: =IFERROR($O23/$N23,"")
E24: =IF($B24="","",$B24*$B$5/1000) | F24: =IF($B24="","",$C24*$B$7/1000*$B$6) | G24: =IF($B24="","",$B$8) | H24: =IF($B24="","",$C24*$B$10) | I24: =IF($B24="","",$D24/60*$B$12) | J24: =IF($B24="","",SUM($E24:$I24)) | K24: =IF($B24="","",$J24*$B$9) | L24: =IF($B24="","",$J24+$K24) | M24: =IFERROR(CEILING($L24/(1-$B$11),1),"") | N24: =IFERROR(CEILING($L24*$B$13/(1-$B$11),1),"") | O24: =IFERROR($N24*(1-$B$11)-$L24,"") | P24: =IFERROR($O24/$N24,"")
E25: =IF($B25="","",$B25*$B$5/1000) | F25: =IF($B25="","",$C25*$B$7/1000*$B$6) | G25: =IF($B25="","",$B$8) | H25: =IF($B25="","",$C25*$B$10) | I25: =IF($B25="","",$D25/60*$B$12) | J25: =IF($B25="","",SUM($E25:$I25)) | K25: =IF($B25="","",$J25*$B$9) | L25: =IF($B25="","",$J25+$K25) | M25: =IFERROR(CEILING($L25/(1-$B$11),1),"") | N25: =IFERROR(CEILING($L25*$B$13/(1-$B$11),1),"") | O25: =IFERROR($N25*(1-$B$11)-$L25,"") | P25: =IFERROR($O25/$N25,"")
E26: =IF($B26="","",$B26*$B$5/1000) | F26: =IF($B26="","",$C26*$B$7/1000*$B$6) | G26: =IF($B26="","",$B$8) | H26: =IF($B26="","",$C26*$B$10) | I26: =IF($B26="","",$D26/60*$B$12) | J26: =IF($B26="","",SUM($E26:$I26)) | K26: =IF($B26="","",$J26*$B$9) | L26: =IF($B26="","",$J26+$K26) | M26: =IFERROR(CEILING($L26/(1-$B$11),1),"") | N26: =IFERROR(CEILING($L26*$B$13/(1-$B$11),1),"") | O26: =IFERROR($N26*(1-$B$11)-$L26,"") | P26: =IFERROR($O26/$N26,"")
E27: =IF($B27="","",$B27*$B$5/1000) | F27: =IF($B27="","",$C27*$B$7/1000*$B$6) | G27: =IF($B27="","",$B$8) | H27: =IF($B27="","",$C27*$B$10) | I27: =IF($B27="","",$D27/60*$B$12) | J27: =IF($B27="","",SUM($E27:$I27)) | K27: =IF($B27="","",$J27*$B$9) | L27: =IF($B27="","",$J27+$K27) | M27: =IFERROR(CEILING($L27/(1-$B$11),1),"") | N27: =IFERROR(CEILING($L27*$B$13/(1-$B$11),1),"") | O27: =IFERROR($N27*(1-$B$11)-$L27,"") | P27: =IFERROR($O27/$N27,"")
E28: =IF($B28="","",$B28*$B$5/1000) | F28: =IF($B28="","",$C28*$B$7/1000*$B$6) | G28: =IF($B28="","",$B$8) | H28: =IF($B28="","",$C28*$B$10) | I28: =IF($B28="","",$D28/60*$B$12) | J28: =IF($B28="","",SUM($E28:$I28)) | K28: =IF($B28="","",$J28*$B$9) | L28: =IF($B28="","",$J28+$K28) | M28: =IFERROR(CEILING($L28/(1-$B$11),1),"") | N28: =IFERROR(CEILING($L28*$B$13/(1-$B$11),1),"") | O28: =IFERROR($N28*(1-$B$11)-$L28,"") | P28: =IFERROR($O28/$N28,"")
E29: =IF($B29="","",$B29*$B$5/1000) | F29: =IF($B29="","",$C29*$B$7/1000*$B$6) | G29: =IF($B29="","",$B$8) | H29: =IF($B29="","",$C29*$B$10) | I29: =IF($B29="","",$D29/60*$B$12) | J29: =IF($B29="","",SUM($E29:$I29)) | K29: =IF($B29="","",$J29*$B$9) | L29: =IF($B29="","",$J29+$K29) | M29: =IFERROR(CEILING($L29/(1-$B$11),1),"") | N29: =IFERROR(CEILING($L29*$B$13/(1-$B$11),1),"") | O29: =IFERROR($N29*(1-$B$11)-$L29,"") | P29: =IFERROR($O29/$N29,"")
... E40: =IF($B40="","",$B40*$B$5/1000) | F40: =IF($B40="","",$C40*$B$7/1000*$B$6) | G40: =IF($B40="","",$B$8) | H40: =IF($B40="","",$C40*$B$10) | I40: =IF($B40="","",$D40/60*$B$12) | J40: =IF($B40="","",SUM($E40:$I40)) | K40: =IF($B40="","",$J40*$B$9) | L40: =IF($B40="","",$J40+$K40) | M40: =IFERROR(CEILING($L40/(1-$B$11),1),"") | N40: =IFERROR(CEILING($L40*$B$13/(1-$B$11),1),"") | O40: =IFERROR($N40*(1-$B$11)-$L40,"") | P40: =IFERROR($O40/$N40,"")
A42: LEGENDA
A43: • Células amarelas com texto azul = você preenche. Todo o resto é fórmula, não edite.
A44: • LANCE MÍNIMO (col. M) = o valor abaixo do qual você trabalha de graça. Nunca abra lance abaixo disso.
A45: • Preço-alvo (col. N) = preço justo de catálogo, já com o multiplicador e a comissão embutidos.
A46: • Lucro e margem consideram a comissão do marketplace, mas NÃO o frete — lance o frete na aba Registro de Vendas.
A47: • A linha de exemplo é só um modelo de formato: apague e coloque as suas peças.

Sheet Registro de Vendas
A1: Registro de Vendas — o que cada peça realmente fechou
A2: Preencha após cada live. O custo é puxado da aba Custo por Peca pelo nome da peça (escreva igual).
A4: Data | B4: Peça | C4: Canal | D4: Preço final | E4: Comissão | F4: Custo da peça | G4: Frete que eu paguei | H4: LUCRO
A5: 09/09/2026 | B5: Dragão articulado M (exemplo) | C5: Live TikTok | D5: 89 | E5: =IF($D5="","",$D5*'Custo por Peca'!$B$11) | F5: =IFERROR(INDEX('Custo por Peca'!$L$17:$L$40,MATCH($B5,'Custo por Peca'!$A$17:$A$40,0)),"") | G5: 0 | H5: =IF($D5="","",$D5-$E5-IF($F5="",0,$F5)-IF($G5="",0,$G5))
E6: =IF($D6="","",$D6*'Custo por Peca'!$B$11) | F6: =IFERROR(INDEX('Custo por Peca'!$L$17:$L$40,MATCH($B6,'Custo por Peca'!$A$17:$A$40,0)),"") | H6: =IF($D6="","",$D6-$E6-IF($F6="",0,$F6)-IF($G6="",0,$G6))
E7: =IF($D7="","",$D7*'Custo por Peca'!$B$11) | F7: =IFERROR(INDEX('Custo por Peca'!$L$17:$L$40,MATCH($B7,'Custo por Peca'!$A$17:$A$40,0)),"") | H7: =IF($D7="","",$D7-$E7-IF($F7="",0,$F7)-IF($G7="",0,$G7))
E8: =IF($D8="","",$D8*'Custo por Peca'!$B$11) | F8: =IFERROR(INDEX('Custo por Peca'!$L$17:$L$40,MATCH($B8,'Custo por Peca'!$A$17:$A$40,0)),"") | H8: =IF($D8="","",$D8-$E8-IF($F8="",0,$F8)-IF($G8="",0,$G8))
E9: =IF($D9="","",$D9*'Custo por Peca'!$B$11) | F9: =IFERROR(INDEX('Custo por Peca'!$L$17:$L$40,MATCH($B9,'Custo por Peca'!$A$17:$A$40,0)),"") | H9: =IF($D9="","",$D9-$E9-IF($F9="",0,$F9)-IF($G9="",0,$G9))
E10: =IF($D10="","",$D10*'Custo por Peca'!$B$11) | F10: =IFERROR(INDEX('Custo por Peca'!$L$17:$L$40,MATCH($B10,'Custo por Peca'!$A$17:$A$40,0)),"") | H10: =IF($D10="","",$D10-$E10-IF($F10="",0,$F10)-IF($G10="",0,$G10))
E11: =IF($D11="","",$D11*'Custo por Peca'!$B$11) | F11: =IFERROR(INDEX('Custo por Peca'!$L$17:$L$40,MATCH($B11,'Custo por Peca'!$A$17:$A$40,0)),"") | H11: =IF($D11="","",$D11-$E11-IF($F11="",0,$F11)-IF($G11="",0,$G11))
E12: =IF($D12="","",$D12*'Custo por Peca'!$B$11) | F12: =IFERROR(INDEX('Custo por Peca'!$L$17:$L$40,MATCH($B12,'Custo por Peca'!$A$17:$A$40,0)),"") | H12: =IF($D12="","",$D12-$E12-IF($F12="",0,$F12)-IF($G12="",0,$G12))
E13: =IF($D13="","",$D13*'Custo por Peca'!$B$11) | F13: =IFERROR(INDEX('Custo por Peca'!$L$17:$L$40,MATCH($B13,'Custo por Peca'!$A$17:$A$40,0)),"") | H13: =IF($D13="","",$D13-$E13-IF($F13="",0,$F13)-IF($G13="",0,$G13))
E14: =IF($D14="","",$D14*'Custo por Peca'!$B$11) | F14: =IFERROR(INDEX('Custo por Peca'!$L$17:$L$40,MATCH($B14,'Custo por Peca'!$A$17:$A$40,0)),"") | H14: =IF($D14="","",$D14-$E14-IF($F14="",0,$F14)-IF($G14="",0,$G14))
E15: =IF($D15="","",$D15*'Custo por Peca'!$B$11) | F15: =IFERROR(INDEX('Custo por Peca'!$L$17:$L$40,MATCH($B15,'Custo por Peca'!$A$17:$A$40,0)),"") | H15: =IF($D15="","",$D15-$E15-IF($F15="",0,$F15)-IF($G15="",0,$G15))
E16: =IF($D16="","",$D16*'Custo por Peca'!$B$11) | F16: =IFERROR(INDEX('Custo por Peca'!$L$17:$L$40,MATCH($B16,'Custo por Peca'!$A$17:$A$40,0)),"") | H16: =IF($D16="","",$D16-$E16-IF($F16="",0,$F16)-IF($G16="",0,$G16))
E17: =IF($D17="","",$D17*'Custo por Peca'!$B$11) | F17: =IFERROR(INDEX('Custo por Peca'!$L$17:$L$40,MATCH($B17,'Custo por Peca'!$A$17:$A$40,0)),"") | H17: =IF($D17="","",$D17-$E17-IF($F17="",0,$F17)-IF($G17="",0,$G17))
... E64: =IF($D64="","",$D64*'Custo por Peca'!$B$11) | F64: =IFERROR(INDEX('Custo por Peca'!$L$17:$L$40,MATCH($B64,'Custo por Peca'!$A$17:$A$40,0)),"") | H64: =IF($D64="","",$D64-$E64-IF($F64="",0,$F64)-IF($G64="",0,$G64))
C66: TOTAIS | D66: =SUM(D5:D64) | E66: =SUM(E5:E64) | F66: =SUM(F5:F64) | G66: =SUM(G5:G64) | H66: =SUM(H5:H64)
C67: Ticket médio | D67: =IFERROR(D66/COUNT(D5:D64),0)
C68: Margem média | D68: =IFERROR(H66/D66,0)
A70: Escreva o nome da peça EXATAMENTE como está na aba Custo por Peca, senão o custo não é encontrado.
